SteamRoller-1.3.1.dist-info/DESCRIPTION.rst
SteamRoller-1.3.1.dist-info/METADATA
SteamRoller-1.3.1.dist-info/RECORD
SteamRoller-1.3.1.dist-info/WHEEL
SteamRoller-1.3.1.dist-info/metadata.json
SteamRoller-1.3.1.dist-info/top_level.txt
steamroller/__init__.py
