Metadata-Version: 2.0
Name: SteamRoller
Version: 1.3.1
Summary: Grid-awareness for SCons build system
Home-page: http://hltcoe.jhu.edu
Author: Tom Lippincott
Author-email: tom@cs.jhu.edu
License: UNKNOWN
Platform: UNKNOWN
Requires-Dist: scons (>=3.0.0)
